umbrellarl_utils/__init__.py
umbrellarl_utils/file_utils.py
umbrellarl_utils-0.0.2.dist-info/LICENSE
umbrellarl_utils-0.0.2.dist-info/METADATA
umbrellarl_utils-0.0.2.dist-info/WHEEL
umbrellarl_utils-0.0.2.dist-info/top_level.txt
umbrellarl_utils-0.0.2.dist-info/RECORD
