Metadata-Version: 2.1
Name: umbrellarl_utils
Version: 0.0.2
Summary: Utilities for UmbrellaRL modules.
Home-page: https://github.com/UmbrellaRL/utils
Author: Christopher Torrington
Author-email: ctorrington1@gmail.com
Classifier: Programming Language :: Python :: 3
Classifier: License :: OSI Approved :: MIT License
Classifier: Operating System :: OS Independent
Requires-Python: >=3.12
License-File: LICENSE
